{
  "users": [
    {
      "id": "f7c8",
      "username": "test@test.com",
      "email": "test1@test.com",
      "password": "test@test.com"
    },
    {
      "id": "419d",
      "username": "test@test.com",
      "email": "test2@test.com",
      "password": "test@test.com"
    },
    {
      "id": "bd7b",
      "username": "test@test.com",
      "email": "test4@test.com",
      "password": "test@test.com"
    },
    {
      "id": "8240",
      "username": "test@test.com",
      "email": "test5@test.com",
      "password": "test@test.com"
    }
  ],
  "bankAccounts": [
    {
      "id": "3e8c",
      "name": "A",
      "type": "Courant",
      "balance": 60,
      "userId": "f7c8",
      "lowBalanceThreshold": 0
    },
    {
      "id": "4575",
      "name": "B",
      "type": "Épargne",
      "balance": 0,
      "userId": "8240",
      "lowBalanceThreshold": 0
    }
  ],
  "transactions": [
    {
      "id": "38f7",
      "accountId": "3e8c",
      "date": "2024-11-13T14:42:15.545Z",
      "type": "deposit",
      "amount": 10
    },
    {
      "id": "b164",
      "accountId": "3e8c",
      "date": "2024-11-13T14:42:25.189Z",
      "type": "deposit",
      "amount": 50
    },
    {
      "id": "f788",
      "accountId": "3e8c",
      "date": "2024-11-13T14:50:51.264Z",
      "type": "deposit",
      "amount": 1
    },
    {
      "id": "96b8",
      "accountId": "3e8c",
      "date": "2024-11-13T14:51:10.686Z",
      "type": "withdrawal",
      "amount": 1
    },
    {
      "id": "b438",
      "accountId": "8de2",
      "date": "2024-11-13T15:54:14.902Z",
      "type": "deposit",
      "amount": 100
    },
    {
      "id": "7e58",
      "accountId": "8de2",
      "date": "2024-11-13T15:54:18.247Z",
      "type": "withdrawal",
      "amount": 95
    },
    {
      "id": "0724",
      "accountId": "3e8c",
      "date": "2024-11-13T19:37:49.410Z",
      "type": "withdrawal",
      "amount": 1
    },
    {
      "id": "b8d3",
      "accountId": "3e8c",
      "date": "2024-11-13T22:18:53.489Z",
      "type": "deposit",
      "amount": 10
    },
    {
      "id": "931b",
      "accountId": "3e8c",
      "date": "2024-11-13T22:19:24.651Z",
      "type": "transfer-out",
      "amount": -10,
      "targetAccountId": null,
      "targetEmail": "test3@test.com"
    }
  ],
  "loginHistory": [
    {
      "id": "e447",
      "userId": "f7c8",
      "date": "2024-11-13T15:19:18.998Z",
      "ip": "IP inconnue",
      "city": "Ville inconnue",
      "region": "Région inconnue",
      "country": "Pays inconnu"
    },
    {
      "id": "463d",
      "userId": "f7c8",
      "date": "2024-11-13T15:19:19.219Z",
      "ip": "IP inconnue",
      "city": "Ville inconnue",
      "region": "Région inconnue",
      "country": "Pays inconnu"
    },
    {
      "id": "3f91",
      "userId": "f7c8",
      "date": "2024-11-13T15:19:19.469Z",
      "ip": "IP inconnue",
      "city": "Ville inconnue",
      "region": "Région inconnue",
      "country": "Pays inconnu"
    },
    {
      "id": "ecd3",
      "userId": "f7c8",
      "date": "2024-11-13T15:19:19.694Z",
      "ip": "IP inconnue",
      "city": "Ville inconnue",
      "region": "Région inconnue",
      "country": "Pays inconnu"
    },
    {
      "id": "6000",
      "userId": "f7c8",
      "date": "2024-11-13T15:19:19.923Z",
      "ip": "IP inconnue",
      "city": "Ville inconnue",
      "region": "Région inconnue",
      "country": "Pays inconnu"
    },
    {
      "id": "1c2a",
      "userId": "f7c8",
      "date": "2024-11-13T15:19:20.141Z",
      "ip": "IP inconnue",
      "city": "Ville inconnue",
      "region": "Région inconnue",
      "country": "Pays inconnu"
    },
    {
      "id": "4fb7",
      "userId": "f7c8",
      "date": "2024-11-13T15:19:20.379Z",
      "ip": "IP inconnue",
      "city": "Ville inconnue",
      "region": "Région inconnue",
      "country": "Pays inconnu"
    },
    {
      "id": "e72e",
      "userId": "f7c8",
      "date": "2024-11-13T15:19:20.654Z",
      "ip": "IP inconnue",
      "city": "Ville inconnue",
      "region": "Région inconnue",
      "country": "Pays inconnu"
    },
    {
      "id": "ee98",
      "userId": "f7c8",
      "date": "2024-11-13T15:19:20.877Z",
      "ip": "IP inconnue",
      "city": "Ville inconnue",
      "region": "Région inconnue",
      "country": "Pays inconnu"
    },
    {
      "id": "2d05",
      "userId": "f7c8",
      "date": "2024-11-13T15:19:21.109Z",
      "ip": "IP inconnue",
      "city": "Ville inconnue",
      "region": "Région inconnue",
      "country": "Pays inconnu"
    },
    {
      "id": "f4c9",
      "userId": "f7c8",
      "date": "2024-11-13T15:19:21.326Z",
      "ip": "IP inconnue",
      "city": "Ville inconnue",
      "region": "Région inconnue",
      "country": "Pays inconnu"
    },
    {
      "id": "0a9b",
      "userId": "f7c8",
      "date": "2024-11-13T15:19:21.595Z",
      "ip": "IP inconnue",
      "city": "Ville inconnue",
      "region": "Région inconnue",
      "country": "Pays inconnu"
    },
    {
      "id": "4dc7",
      "userId": "f7c8",
      "date": "2024-11-13T15:19:21.851Z",
      "ip": "IP inconnue",
      "city": "Ville inconnue",
      "region": "Région inconnue",
      "country": "Pays inconnu"
    },
    {
      "id": "4c93",
      "userId": "f7c8",
      "date": "2024-11-13T15:19:22.154Z",
      "ip": "IP inconnue",
      "city": "Ville inconnue",
      "region": "Région inconnue",
      "country": "Pays inconnu"
    },
    {
      "id": "8a7e",
      "userId": "f7c8",
      "date": "2024-11-13T15:19:22.361Z",
      "ip": "IP inconnue",
      "city": "Ville inconnue",
      "region": "Région inconnue",
      "country": "Pays inconnu"
    },
    {
      "id": "f522",
      "userId": "f7c8",
      "date": "2024-11-13T15:19:22.617Z",
      "ip": "IP inconnue",
      "city": "Ville inconnue",
      "region": "Région inconnue",
      "country": "Pays inconnu"
    },
    {
      "id": "3777",
      "userId": "f7c8",
      "date": "2024-11-13T15:19:22.867Z",
      "ip": "IP inconnue",
      "city": "Ville inconnue",
      "region": "Région inconnue",
      "country": "Pays inconnu"
    },
    {
      "id": "73b6",
      "userId": "f7c8",
      "date": "2024-11-13T15:19:23.110Z",
      "ip": "IP inconnue",
      "city": "Ville inconnue",
      "region": "Région inconnue",
      "country": "Pays inconnu"
    },
    {
      "id": "d3e3",
      "userId": "f7c8",
      "date": "2024-11-13T15:19:23.342Z",
      "ip": "IP inconnue",
      "city": "Ville inconnue",
      "region": "Région inconnue",
      "country": "Pays inconnu"
    },
    {
      "id": "4ff0",
      "userId": "f7c8",
      "date": "2024-11-13T15:19:23.573Z",
      "ip": "IP inconnue",
      "city": "Ville inconnue",
      "region": "Région inconnue",
      "country": "Pays inconnu"
    },
    {
      "id": "e0bb",
      "userId": "f7c8",
      "date": "2024-11-13T15:19:23.835Z",
      "ip": "IP inconnue",
      "city": "Ville inconnue",
      "region": "Région inconnue",
      "country": "Pays inconnu"
    },
    {
      "id": "e282",
      "userId": "f7c8",
      "date": "2024-11-13T15:19:24.095Z",
      "ip": "IP inconnue",
      "city": "Ville inconnue",
      "region": "Région inconnue",
      "country": "Pays inconnu"
    },
    {
      "id": "1520",
      "userId": "f7c8",
      "date": "2024-11-13T15:19:24.372Z",
      "ip": "IP inconnue",
      "city": "Ville inconnue",
      "region": "Région inconnue",
      "country": "Pays inconnu"
    },
    {
      "id": "c54e",
      "userId": "f7c8",
      "date": "2024-11-13T15:19:24.635Z",
      "ip": "IP inconnue",
      "city": "Ville inconnue",
      "region": "Région inconnue",
      "country": "Pays inconnu"
    },
    {
      "id": "67c8",
      "userId": "f7c8",
      "date": "2024-11-13T15:19:24.903Z",
      "ip": "IP inconnue",
      "city": "Ville inconnue",
      "region": "Région inconnue",
      "country": "Pays inconnu"
    },
    {
      "id": "a7ce",
      "userId": "f7c8",
      "date": "2024-11-13T15:19:25.167Z",
      "ip": "IP inconnue",
      "city": "Ville inconnue",
      "region": "Région inconnue",
      "country": "Pays inconnu"
    },
    {
      "id": "5af7",
      "userId": "f7c8",
      "date": "2024-11-13T15:19:25.396Z",
      "ip": "IP inconnue",
      "city": "Ville inconnue",
      "region": "Région inconnue",
      "country": "Pays inconnu"
    },
    {
      "id": "fefe",
      "userId": "f7c8",
      "date": "2024-11-13T15:19:25.646Z",
      "ip": "IP inconnue",
      "city": "Ville inconnue",
      "region": "Région inconnue",
      "country": "Pays inconnu"
    },
    {
      "id": "402a",
      "userId": "f7c8",
      "date": "2024-11-13T15:19:25.879Z",
      "ip": "IP inconnue",
      "city": "Ville inconnue",
      "region": "Région inconnue",
      "country": "Pays inconnu"
    },
    {
      "id": "58c3",
      "userId": "f7c8",
      "date": "2024-11-13T15:19:26.090Z",
      "ip": "IP inconnue",
      "city": "Ville inconnue",
      "region": "Région inconnue",
      "country": "Pays inconnu"
    },
    {
      "id": "ccb9",
      "userId": "f7c8",
      "date": "2024-11-13T15:19:26.362Z",
      "ip": "IP inconnue",
      "city": "Ville inconnue",
      "region": "Région inconnue",
      "country": "Pays inconnu"
    },
    {
      "id": "f738",
      "userId": "f7c8",
      "date": "2024-11-13T15:19:26.591Z",
      "ip": "IP inconnue",
      "city": "Ville inconnue",
      "region": "Région inconnue",
      "country": "Pays inconnu"
    },
    {
      "id": "4438",
      "userId": "f7c8",
      "date": "2024-11-13T15:19:26.858Z",
      "ip": "IP inconnue",
      "city": "Ville inconnue",
      "region": "Région inconnue",
      "country": "Pays inconnu"
    },
    {
      "id": "2835",
      "userId": "f7c8",
      "date": "2024-11-13T15:19:27.125Z",
      "ip": "IP inconnue",
      "city": "Ville inconnue",
      "region": "Région inconnue",
      "country": "Pays inconnu"
    },
    {
      "id": "6608",
      "userId": "f7c8",
      "date": "2024-11-13T15:19:27.429Z",
      "ip": "IP inconnue",
      "city": "Ville inconnue",
      "region": "Région inconnue",
      "country": "Pays inconnu"
    },
    {
      "id": "5d60",
      "userId": "f7c8",
      "date": "2024-11-13T15:19:27.679Z",
      "ip": "IP inconnue",
      "city": "Ville inconnue",
      "region": "Région inconnue",
      "country": "Pays inconnu"
    },
    {
      "id": "4a8d",
      "userId": "f7c8",
      "date": "2024-11-13T15:19:27.931Z",
      "ip": "IP inconnue",
      "city": "Ville inconnue",
      "region": "Région inconnue",
      "country": "Pays inconnu"
    },
    {
      "id": "51f6",
      "userId": "f7c8",
      "date": "2024-11-13T15:19:28.201Z",
      "ip": "IP inconnue",
      "city": "Ville inconnue",
      "region": "Région inconnue",
      "country": "Pays inconnu"
    },
    {
      "id": "16d5",
      "userId": "f7c8",
      "date": "2024-11-13T15:19:28.412Z",
      "ip": "IP inconnue",
      "city": "Ville inconnue",
      "region": "Région inconnue",
      "country": "Pays inconnu"
    },
    {
      "id": "e7f0",
      "userId": "f7c8",
      "date": "2024-11-13T15:19:28.688Z",
      "ip": "IP inconnue",
      "city": "Ville inconnue",
      "region": "Région inconnue",
      "country": "Pays inconnu"
    },
    {
      "id": "fc5f",
      "userId": "f7c8",
      "date": "2024-11-13T15:19:28.906Z",
      "ip": "IP inconnue",
      "city": "Ville inconnue",
      "region": "Région inconnue",
      "country": "Pays inconnu"
    },
    {
      "id": "d704",
      "userId": "f7c8",
      "date": "2024-11-13T15:19:29.136Z",
      "ip": "IP inconnue",
      "city": "Ville inconnue",
      "region": "Région inconnue",
      "country": "Pays inconnu"
    },
    {
      "id": "e681",
      "userId": "f7c8",
      "date": "2024-11-13T15:19:29.356Z",
      "ip": "IP inconnue",
      "city": "Ville inconnue",
      "region": "Région inconnue",
      "country": "Pays inconnu"
    },
    {
      "id": "3489",
      "userId": "f7c8",
      "date": "2024-11-13T15:19:29.578Z",
      "ip": "IP inconnue",
      "city": "Ville inconnue",
      "region": "Région inconnue",
      "country": "Pays inconnu"
    },
    {
      "id": "e63b",
      "userId": "f7c8",
      "date": "2024-11-13T15:19:29.789Z",
      "ip": "IP inconnue",
      "city": "Ville inconnue",
      "region": "Région inconnue",
      "country": "Pays inconnu"
    },
    {
      "id": "11d9",
      "userId": "f7c8",
      "date": "2024-11-13T15:19:30.050Z",
      "ip": "IP inconnue",
      "city": "Ville inconnue",
      "region": "Région inconnue",
      "country": "Pays inconnu"
    },
    {
      "id": "01d4",
      "userId": "f7c8",
      "date": "2024-11-13T15:19:30.312Z",
      "ip": "IP inconnue",
      "city": "Ville inconnue",
      "region": "Région inconnue",
      "country": "Pays inconnu"
    },
    {
      "id": "b5ea",
      "userId": "f7c8",
      "date": "2024-11-13T15:19:30.587Z",
      "ip": "IP inconnue",
      "city": "Ville inconnue",
      "region": "Région inconnue",
      "country": "Pays inconnu"
    },
    {
      "id": "451b",
      "userId": "f7c8",
      "date": "2024-11-13T15:19:30.841Z",
      "ip": "IP inconnue",
      "city": "Ville inconnue",
      "region": "Région inconnue",
      "country": "Pays inconnu"
    },
    {
      "id": "b1b3",
      "userId": "f7c8",
      "date": "2024-11-13T15:19:31.105Z",
      "ip": "IP inconnue",
      "city": "Ville inconnue",
      "region": "Région inconnue",
      "country": "Pays inconnu"
    },
    {
      "id": "16b1",
      "userId": "f7c8",
      "date": "2024-11-13T15:19:31.370Z",
      "ip": "IP inconnue",
      "city": "Ville inconnue",
      "region": "Région inconnue",
      "country": "Pays inconnu"
    },
    {
      "id": "a223",
      "userId": "f7c8",
      "date": "2024-11-13T15:19:31.598Z",
      "ip": "IP inconnue",
      "city": "Ville inconnue",
      "region": "Région inconnue",
      "country": "Pays inconnu"
    },
    {
      "id": "faab",
      "userId": "f7c8",
      "date": "2024-11-13T15:19:31.876Z",
      "ip": "IP inconnue",
      "city": "Ville inconnue",
      "region": "Région inconnue",
      "country": "Pays inconnu"
    },
    {
      "id": "a802",
      "userId": "f7c8",
      "date": "2024-11-13T15:19:32.140Z",
      "ip": "IP inconnue",
      "city": "Ville inconnue",
      "region": "Région inconnue",
      "country": "Pays inconnu"
    },
    {
      "id": "1772",
      "userId": "f7c8",
      "date": "2024-11-13T15:19:32.432Z",
      "ip": "IP inconnue",
      "city": "Ville inconnue",
      "region": "Région inconnue",
      "country": "Pays inconnu"
    },
    {
      "id": "af86",
      "userId": "f7c8",
      "date": "2024-11-13T15:19:32.670Z",
      "ip": "IP inconnue",
      "city": "Ville inconnue",
      "region": "Région inconnue",
      "country": "Pays inconnu"
    },
    {
      "id": "5e34",
      "userId": "f7c8",
      "date": "2024-11-13T15:19:32.988Z",
      "ip": "IP inconnue",
      "city": "Ville inconnue",
      "region": "Région inconnue",
      "country": "Pays inconnu"
    },
    {
      "id": "d778",
      "userId": "f7c8",
      "date": "2024-11-13T15:19:33.210Z",
      "ip": "IP inconnue",
      "city": "Ville inconnue",
      "region": "Région inconnue",
      "country": "Pays inconnu"
    },
    {
      "id": "53f7",
      "userId": "f7c8",
      "date": "2024-11-13T15:19:33.527Z",
      "ip": "IP inconnue",
      "city": "Ville inconnue",
      "region": "Région inconnue",
      "country": "Pays inconnu"
    },
    {
      "id": "1802",
      "userId": "f7c8",
      "date": "2024-11-13T15:19:33.734Z",
      "ip": "IP inconnue",
      "city": "Ville inconnue",
      "region": "Région inconnue",
      "country": "Pays inconnu"
    },
    {
      "id": "fcab",
      "userId": "f7c8",
      "date": "2024-11-13T15:19:34.001Z",
      "ip": "IP inconnue",
      "city": "Ville inconnue",
      "region": "Région inconnue",
      "country": "Pays inconnu"
    },
    {
      "id": "1865",
      "userId": "f7c8",
      "date": "2024-11-13T15:19:34.205Z",
      "ip": "IP inconnue",
      "city": "Ville inconnue",
      "region": "Région inconnue",
      "country": "Pays inconnu"
    },
    {
      "id": "d925",
      "userId": "f7c8",
      "date": "2024-11-13T15:19:34.441Z",
      "ip": "IP inconnue",
      "city": "Ville inconnue",
      "region": "Région inconnue",
      "country": "Pays inconnu"
    },
    {
      "id": "8171",
      "userId": "f7c8",
      "date": "2024-11-13T15:19:34.669Z",
      "ip": "IP inconnue",
      "city": "Ville inconnue",
      "region": "Région inconnue",
      "country": "Pays inconnu"
    },
    {
      "id": "538e",
      "userId": "f7c8",
      "date": "2024-11-13T15:19:34.890Z",
      "ip": "IP inconnue",
      "city": "Ville inconnue",
      "region": "Région inconnue",
      "country": "Pays inconnu"
    },
    {
      "id": "267a",
      "userId": "f7c8",
      "date": "2024-11-13T15:19:35.117Z",
      "ip": "IP inconnue",
      "city": "Ville inconnue",
      "region": "Région inconnue",
      "country": "Pays inconnu"
    },
    {
      "id": "7fc1",
      "userId": "f7c8",
      "date": "2024-11-13T15:19:35.358Z",
      "ip": "IP inconnue",
      "city": "Ville inconnue",
      "region": "Région inconnue",
      "country": "Pays inconnu"
    },
    {
      "id": "3abf",
      "userId": "f7c8",
      "date": "2024-11-13T15:19:35.582Z",
      "ip": "IP inconnue",
      "city": "Ville inconnue",
      "region": "Région inconnue",
      "country": "Pays inconnu"
    },
    {
      "id": "d2a8",
      "userId": "f7c8",
      "date": "2024-11-13T15:19:35.805Z",
      "ip": "IP inconnue",
      "city": "Ville inconnue",
      "region": "Région inconnue",
      "country": "Pays inconnu"
    },
    {
      "id": "b2c3",
      "userId": "f7c8",
      "date": "2024-11-13T15:19:36.041Z",
      "ip": "IP inconnue",
      "city": "Ville inconnue",
      "region": "Région inconnue",
      "country": "Pays inconnu"
    },
    {
      "id": "b4f1",
      "userId": "f7c8",
      "date": "2024-11-13T15:19:36.270Z",
      "ip": "IP inconnue",
      "city": "Ville inconnue",
      "region": "Région inconnue",
      "country": "Pays inconnu"
    },
    {
      "id": "f1de",
      "userId": "f7c8",
      "date": "2024-11-13T15:19:36.483Z",
      "ip": "IP inconnue",
      "city": "Ville inconnue",
      "region": "Région inconnue",
      "country": "Pays inconnu"
    },
    {
      "id": "e826",
      "userId": "f7c8",
      "date": "2024-11-13T15:19:36.702Z",
      "ip": "IP inconnue",
      "city": "Ville inconnue",
      "region": "Région inconnue",
      "country": "Pays inconnu"
    },
    {
      "id": "4172",
      "userId": "f7c8",
      "date": "2024-11-13T15:19:36.937Z",
      "ip": "IP inconnue",
      "city": "Ville inconnue",
      "region": "Région inconnue",
      "country": "Pays inconnu"
    },
    {
      "id": "cacf",
      "userId": "f7c8",
      "date": "2024-11-13T15:19:37.170Z",
      "ip": "IP inconnue",
      "city": "Ville inconnue",
      "region": "Région inconnue",
      "country": "Pays inconnu"
    },
    {
      "id": "0012",
      "userId": "f7c8",
      "date": "2024-11-13T15:19:37.426Z",
      "ip": "IP inconnue",
      "city": "Ville inconnue",
      "region": "Région inconnue",
      "country": "Pays inconnu"
    },
    {
      "id": "03fe",
      "userId": "f7c8",
      "date": "2024-11-13T15:19:37.705Z",
      "ip": "IP inconnue",
      "city": "Ville inconnue",
      "region": "Région inconnue",
      "country": "Pays inconnu"
    },
    {
      "id": "bed2",
      "userId": "f7c8",
      "date": "2024-11-13T15:19:38.031Z",
      "ip": "IP inconnue",
      "city": "Ville inconnue",
      "region": "Région inconnue",
      "country": "Pays inconnu"
    },
    {
      "id": "c69b",
      "userId": "f7c8",
      "date": "2024-11-13T15:19:38.232Z",
      "ip": "IP inconnue",
      "city": "Ville inconnue",
      "region": "Région inconnue",
      "country": "Pays inconnu"
    },
    {
      "id": "1e71",
      "userId": "f7c8",
      "date": "2024-11-13T15:19:38.463Z",
      "ip": "IP inconnue",
      "city": "Ville inconnue",
      "region": "Région inconnue",
      "country": "Pays inconnu"
    },
    {
      "id": "3bd1",
      "userId": "f7c8",
      "date": "2024-11-13T15:19:38.682Z",
      "ip": "IP inconnue",
      "city": "Ville inconnue",
      "region": "Région inconnue",
      "country": "Pays inconnu"
    },
    {
      "id": "9a45",
      "userId": "f7c8",
      "date": "2024-11-13T15:19:38.922Z",
      "ip": "IP inconnue",
      "city": "Ville inconnue",
      "region": "Région inconnue",
      "country": "Pays inconnu"
    },
    {
      "id": "af69",
      "userId": "f7c8",
      "date": "2024-11-13T15:19:39.190Z",
      "ip": "IP inconnue",
      "city": "Ville inconnue",
      "region": "Région inconnue",
      "country": "Pays inconnu"
    },
    {
      "id": "4c92",
      "userId": "f7c8",
      "date": "2024-11-13T15:19:39.433Z",
      "ip": "IP inconnue",
      "city": "Ville inconnue",
      "region": "Région inconnue",
      "country": "Pays inconnu"
    },
    {
      "id": "9210",
      "userId": "f7c8",
      "date": "2024-11-13T15:19:39.696Z",
      "ip": "IP inconnue",
      "city": "Ville inconnue",
      "region": "Région inconnue",
      "country": "Pays inconnu"
    },
    {
      "id": "1381",
      "userId": "f7c8",
      "date": "2024-11-13T15:19:39.953Z",
      "ip": "IP inconnue",
      "city": "Ville inconnue",
      "region": "Région inconnue",
      "country": "Pays inconnu"
    },
    {
      "id": "871d",
      "userId": "f7c8",
      "date": "2024-11-13T15:19:40.223Z",
      "ip": "IP inconnue",
      "city": "Ville inconnue",
      "region": "Région inconnue",
      "country": "Pays inconnu"
    },
    {
      "id": "e897",
      "userId": "f7c8",
      "date": "2024-11-13T15:19:40.487Z",
      "ip": "IP inconnue",
      "city": "Ville inconnue",
      "region": "Région inconnue",
      "country": "Pays inconnu"
    },
    {
      "id": "0bfb",
      "userId": "f7c8",
      "date": "2024-11-13T15:19:40.751Z",
      "ip": "IP inconnue",
      "city": "Ville inconnue",
      "region": "Région inconnue",
      "country": "Pays inconnu"
    },
    {
      "id": "48eb",
      "userId": "f7c8",
      "date": "2024-11-13T15:19:40.961Z",
      "ip": "IP inconnue",
      "city": "Ville inconnue",
      "region": "Région inconnue",
      "country": "Pays inconnu"
    },
    {
      "id": "3700",
      "userId": "f7c8",
      "date": "2024-11-13T15:19:41.230Z",
      "ip": "IP inconnue",
      "city": "Ville inconnue",
      "region": "Région inconnue",
      "country": "Pays inconnu"
    },
    {
      "id": "c4aa",
      "userId": "f7c8",
      "date": "2024-11-13T15:19:41.425Z",
      "ip": "IP inconnue",
      "city": "Ville inconnue",
      "region": "Région inconnue",
      "country": "Pays inconnu"
    },
    {
      "id": "33cd",
      "userId": "f7c8",
      "date": "2024-11-13T15:19:41.640Z",
      "ip": "IP inconnue",
      "city": "Ville inconnue",
      "region": "Région inconnue",
      "country": "Pays inconnu"
    },
    {
      "id": "c90b",
      "userId": "f7c8",
      "date": "2024-11-13T15:21:56.031Z",
      "ip": "IP inconnue",
      "city": "Ville inconnue",
      "region": "Région inconnue",
      "country": "Pays inconnu"
    },
    {
      "id": "8034",
      "userId": "f7c8",
      "date": "2024-11-13T15:21:56.257Z",
      "ip": "IP inconnue",
      "city": "Ville inconnue",
      "region": "Région inconnue",
      "country": "Pays inconnu"
    },
    {
      "id": "42bd",
      "userId": "f7c8",
      "date": "2024-11-13T15:21:56.504Z",
      "ip": "IP inconnue",
      "city": "Ville inconnue",
      "region": "Région inconnue",
      "country": "Pays inconnu"
    },
    {
      "id": "719b",
      "userId": "f7c8",
      "date": "2024-11-13T15:21:56.723Z",
      "ip": "IP inconnue",
      "city": "Ville inconnue",
      "region": "Région inconnue",
      "country": "Pays inconnu"
    },
    {
      "id": "9127",
      "userId": "f7c8",
      "date": "2024-11-13T15:21:56.961Z",
      "ip": "IP inconnue",
      "city": "Ville inconnue",
      "region": "Région inconnue",
      "country": "Pays inconnu"
    },
    {
      "id": "4db9",
      "userId": "f7c8",
      "date": "2024-11-13T15:21:57.215Z",
      "ip": "IP inconnue",
      "city": "Ville inconnue",
      "region": "Région inconnue",
      "country": "Pays inconnu"
    },
    {
      "id": "4f11",
      "userId": "f7c8",
      "date": "2024-11-13T15:21:57.456Z",
      "ip": "IP inconnue",
      "city": "Ville inconnue",
      "region": "Région inconnue",
      "country": "Pays inconnu"
    },
    {
      "id": "3c1c",
      "userId": "f7c8",
      "date": "2024-11-13T15:21:57.697Z",
      "ip": "IP inconnue",
      "city": "Ville inconnue",
      "region": "Région inconnue",
      "country": "Pays inconnu"
    },
    {
      "id": "71c8",
      "userId": "f7c8",
      "date": "2024-11-13T15:21:57.946Z",
      "ip": "IP inconnue",
      "city": "Ville inconnue",
      "region": "Région inconnue",
      "country": "Pays inconnu"
    },
    {
      "id": "8d33",
      "userId": "f7c8",
      "date": "2024-11-13T15:21:58.191Z",
      "ip": "IP inconnue",
      "city": "Ville inconnue",
      "region": "Région inconnue",
      "country": "Pays inconnu"
    },
    {
      "id": "3638",
      "userId": "f7c8",
      "date": "2024-11-13T15:21:58.428Z",
      "ip": "IP inconnue",
      "city": "Ville inconnue",
      "region": "Région inconnue",
      "country": "Pays inconnu"
    },
    {
      "id": "5dfe",
      "userId": "f7c8",
      "date": "2024-11-13T15:21:58.637Z",
      "ip": "IP inconnue",
      "city": "Ville inconnue",
      "region": "Région inconnue",
      "country": "Pays inconnu"
    },
    {
      "id": "227c",
      "userId": "f7c8",
      "date": "2024-11-13T15:21:58.855Z",
      "ip": "IP inconnue",
      "city": "Ville inconnue",
      "region": "Région inconnue",
      "country": "Pays inconnu"
    },
    {
      "id": "a8d9",
      "userId": "f7c8",
      "date": "2024-11-13T15:21:59.076Z",
      "ip": "IP inconnue",
      "city": "Ville inconnue",
      "region": "Région inconnue",
      "country": "Pays inconnu"
    },
    {
      "id": "88f9",
      "userId": "f7c8",
      "date": "2024-11-13T15:21:59.293Z",
      "ip": "IP inconnue",
      "city": "Ville inconnue",
      "region": "Région inconnue",
      "country": "Pays inconnu"
    },
    {
      "id": "9bbe",
      "userId": "f7c8",
      "date": "2024-11-13T15:21:59.511Z",
      "ip": "IP inconnue",
      "city": "Ville inconnue",
      "region": "Région inconnue",
      "country": "Pays inconnu"
    },
    {
      "id": "f810",
      "userId": "f7c8",
      "date": "2024-11-13T15:21:59.705Z",
      "ip": "IP inconnue",
      "city": "Ville inconnue",
      "region": "Région inconnue",
      "country": "Pays inconnu"
    },
    {
      "id": "5d84",
      "userId": "f7c8",
      "date": "2024-11-13T15:21:59.919Z",
      "ip": "IP inconnue",
      "city": "Ville inconnue",
      "region": "Région inconnue",
      "country": "Pays inconnu"
    },
    {
      "id": "6082",
      "userId": "f7c8",
      "date": "2024-11-13T15:24:08.353Z",
      "ip": "IP inconnue",
      "city": "Ville inconnue",
      "region": "Région inconnue",
      "country": "Pays inconnu"
    },
    {
      "id": "8d43",
      "userId": "f7c8",
      "date": "2024-11-13T15:24:08.554Z",
      "ip": "IP inconnue",
      "city": "Ville inconnue",
      "region": "Région inconnue",
      "country": "Pays inconnu"
    },
    {
      "id": "69da",
      "userId": "f7c8",
      "date": "2024-11-13T15:24:08.787Z",
      "ip": "IP inconnue",
      "city": "Ville inconnue",
      "region": "Région inconnue",
      "country": "Pays inconnu"
    },
    {
      "id": "3b7e",
      "userId": "f7c8",
      "date": "2024-11-13T15:24:09.030Z",
      "ip": "IP inconnue",
      "city": "Ville inconnue",
      "region": "Région inconnue",
      "country": "Pays inconnu"
    },
    {
      "id": "0f95",
      "userId": "f7c8",
      "date": "2024-11-13T15:24:09.237Z",
      "ip": "IP inconnue",
      "city": "Ville inconnue",
      "region": "Région inconnue",
      "country": "Pays inconnu"
    },
    {
      "id": "f22b",
      "userId": "f7c8",
      "date": "2024-11-13T15:24:09.467Z",
      "ip": "IP inconnue",
      "city": "Ville inconnue",
      "region": "Région inconnue",
      "country": "Pays inconnu"
    },
    {
      "id": "098e",
      "userId": "f7c8",
      "date": "2024-11-13T15:24:09.697Z",
      "ip": "IP inconnue",
      "city": "Ville inconnue",
      "region": "Région inconnue",
      "country": "Pays inconnu"
    },
    {
      "id": "f584",
      "userId": "f7c8",
      "date": "2024-11-13T15:24:09.897Z",
      "ip": "IP inconnue",
      "city": "Ville inconnue",
      "region": "Région inconnue",
      "country": "Pays inconnu"
    },
    {
      "id": "7bae",
      "userId": "f7c8",
      "date": "2024-11-13T15:24:10.114Z",
      "ip": "IP inconnue",
      "city": "Ville inconnue",
      "region": "Région inconnue",
      "country": "Pays inconnu"
    },
    {
      "id": "e073",
      "userId": "f7c8",
      "date": "2024-11-13T15:24:10.343Z",
      "ip": "IP inconnue",
      "city": "Ville inconnue",
      "region": "Région inconnue",
      "country": "Pays inconnu"
    },
    {
      "id": "3375",
      "userId": "f7c8",
      "date": "2024-11-13T15:24:10.552Z",
      "ip": "IP inconnue",
      "city": "Ville inconnue",
      "region": "Région inconnue",
      "country": "Pays inconnu"
    },
    {
      "id": "c46e",
      "userId": "f7c8",
      "date": "2024-11-13T15:24:10.762Z",
      "ip": "IP inconnue",
      "city": "Ville inconnue",
      "region": "Région inconnue",
      "country": "Pays inconnu"
    },
    {
      "id": "94dd",
      "userId": "f7c8",
      "date": "2024-11-13T15:24:10.993Z",
      "ip": "IP inconnue",
      "city": "Ville inconnue",
      "region": "Région inconnue",
      "country": "Pays inconnu"
    },
    {
      "id": "cd98",
      "userId": "f7c8",
      "date": "2024-11-13T15:24:11.202Z",
      "ip": "IP inconnue",
      "city": "Ville inconnue",
      "region": "Région inconnue",
      "country": "Pays inconnu"
    },
    {
      "id": "cf29",
      "userId": "f7c8",
      "date": "2024-11-13T15:24:11.451Z",
      "ip": "IP inconnue",
      "city": "Ville inconnue",
      "region": "Région inconnue",
      "country": "Pays inconnu"
    },
    {
      "id": "7c0f",
      "userId": "f7c8",
      "date": "2024-11-13T15:24:11.676Z",
      "ip": "IP inconnue",
      "city": "Ville inconnue",
      "region": "Région inconnue",
      "country": "Pays inconnu"
    },
    {
      "id": "8bc9",
      "userId": "f7c8",
      "date": "2024-11-13T15:24:11.907Z",
      "ip": "IP inconnue",
      "city": "Ville inconnue",
      "region": "Région inconnue",
      "country": "Pays inconnu"
    },
    {
      "id": "706e",
      "userId": "f7c8",
      "date": "2024-11-13T15:24:12.141Z",
      "ip": "IP inconnue",
      "city": "Ville inconnue",
      "region": "Région inconnue",
      "country": "Pays inconnu"
    },
    {
      "id": "a177",
      "userId": "f7c8",
      "date": "2024-11-13T15:24:12.380Z",
      "ip": "IP inconnue",
      "city": "Ville inconnue",
      "region": "Région inconnue",
      "country": "Pays inconnu"
    },
    {
      "id": "c171",
      "userId": "f7c8",
      "date": "2024-11-13T15:24:12.600Z",
      "ip": "IP inconnue",
      "city": "Ville inconnue",
      "region": "Région inconnue",
      "country": "Pays inconnu"
    },
    {
      "id": "497d",
      "userId": "f7c8",
      "date": "2024-11-13T15:24:12.820Z",
      "ip": "IP inconnue",
      "city": "Ville inconnue",
      "region": "Région inconnue",
      "country": "Pays inconnu"
    },
    {
      "id": "7e35",
      "userId": "f7c8",
      "date": "2024-11-13T15:24:13.026Z",
      "ip": "IP inconnue",
      "city": "Ville inconnue",
      "region": "Région inconnue",
      "country": "Pays inconnu"
    },
    {
      "id": "2e8a",
      "userId": "f7c8",
      "date": "2024-11-13T15:24:13.234Z",
      "ip": "IP inconnue",
      "city": "Ville inconnue",
      "region": "Région inconnue",
      "country": "Pays inconnu"
    },
    {
      "id": "5f35",
      "userId": "f7c8",
      "date": "2024-11-13T15:24:13.451Z",
      "ip": "IP inconnue",
      "city": "Ville inconnue",
      "region": "Région inconnue",
      "country": "Pays inconnu"
    },
    {
      "id": "266d",
      "userId": "f7c8",
      "date": "2024-11-13T15:24:13.671Z",
      "ip": "IP inconnue",
      "city": "Ville inconnue",
      "region": "Région inconnue",
      "country": "Pays inconnu"
    },
    {
      "id": "ba3a",
      "userId": "f7c8",
      "date": "2024-11-13T15:24:13.888Z",
      "ip": "IP inconnue",
      "city": "Ville inconnue",
      "region": "Région inconnue",
      "country": "Pays inconnu"
    },
    {
      "id": "715a",
      "userId": "f7c8",
      "date": "2024-11-13T15:24:14.133Z",
      "ip": "IP inconnue",
      "city": "Ville inconnue",
      "region": "Région inconnue",
      "country": "Pays inconnu"
    },
    {
      "id": "b318",
      "userId": "f7c8",
      "date": "2024-11-13T15:24:14.336Z",
      "ip": "IP inconnue",
      "city": "Ville inconnue",
      "region": "Région inconnue",
      "country": "Pays inconnu"
    },
    {
      "id": "1026",
      "userId": "f7c8",
      "date": "2024-11-13T15:24:14.546Z",
      "ip": "IP inconnue",
      "city": "Ville inconnue",
      "region": "Région inconnue",
      "country": "Pays inconnu"
    },
    {
      "id": "43e9",
      "userId": "f7c8",
      "date": "2024-11-13T15:24:14.742Z",
      "ip": "IP inconnue",
      "city": "Ville inconnue",
      "region": "Région inconnue",
      "country": "Pays inconnu"
    },
    {
      "id": "0600",
      "userId": "f7c8",
      "date": "2024-11-13T15:24:14.992Z",
      "ip": "IP inconnue",
      "city": "Ville inconnue",
      "region": "Région inconnue",
      "country": "Pays inconnu"
    },
    {
      "id": "f177",
      "userId": "f7c8",
      "date": "2024-11-13T15:24:15.213Z",
      "ip": "IP inconnue",
      "city": "Ville inconnue",
      "region": "Région inconnue",
      "country": "Pays inconnu"
    },
    {
      "id": "dfa7",
      "userId": "f7c8",
      "date": "2024-11-13T15:24:15.442Z",
      "ip": "IP inconnue",
      "city": "Ville inconnue",
      "region": "Région inconnue",
      "country": "Pays inconnu"
    },
    {
      "id": "f85b",
      "userId": "f7c8",
      "date": "2024-11-13T15:24:15.665Z",
      "ip": "IP inconnue",
      "city": "Ville inconnue",
      "region": "Région inconnue",
      "country": "Pays inconnu"
    },
    {
      "id": "0ff1",
      "userId": "f7c8",
      "date": "2024-11-13T15:24:15.911Z",
      "ip": "IP inconnue",
      "city": "Ville inconnue",
      "region": "Région inconnue",
      "country": "Pays inconnu"
    },
    {
      "id": "095b",
      "userId": "f7c8",
      "date": "2024-11-13T15:24:16.135Z",
      "ip": "IP inconnue",
      "city": "Ville inconnue",
      "region": "Région inconnue",
      "country": "Pays inconnu"
    },
    {
      "id": "7bb7",
      "userId": "f7c8",
      "date": "2024-11-13T15:24:16.337Z",
      "ip": "IP inconnue",
      "city": "Ville inconnue",
      "region": "Région inconnue",
      "country": "Pays inconnu"
    },
    {
      "id": "3091",
      "userId": "f7c8",
      "date": "2024-11-13T15:24:16.569Z",
      "ip": "IP inconnue",
      "city": "Ville inconnue",
      "region": "Région inconnue",
      "country": "Pays inconnu"
    },
    {
      "id": "5a2b",
      "userId": "f7c8",
      "date": "2024-11-13T15:24:16.778Z",
      "ip": "IP inconnue",
      "city": "Ville inconnue",
      "region": "Région inconnue",
      "country": "Pays inconnu"
    },
    {
      "id": "7a4b",
      "userId": "f7c8",
      "date": "2024-11-13T15:27:03.111Z"
    },
    {
      "id": "5a5f",
      "userId": "f7c8",
      "date": "2024-11-13T15:48:26.878Z"
    },
    {
      "id": "b1cb",
      "userId": "f7c8",
      "date": "2024-11-13T15:48:40.831Z"
    },
    {
      "id": "0a27",
      "userId": "f7c8",
      "date": "2024-11-13T15:49:13.473Z"
    },
    {
      "id": "1e0c",
      "userId": "bd7b",
      "date": "2024-11-13T15:51:01.842Z"
    },
    {
      "id": "637a",
      "userId": "f7c8",
      "date": "2024-11-13T15:52:09.884Z"
    },
    {
      "id": "5007",
      "userId": "8240",
      "date": "2024-11-13T15:56:03.576Z"
    },
    {
      "id": "cdd3",
      "userId": "f7c8",
      "date": "2024-11-13T18:43:59.051Z"
    },
    {
      "id": "819e",
      "userId": "f7c8",
      "date": "2024-11-13T18:56:48.252Z"
    },
    {
      "id": "669d",
      "userId": "f7c8",
      "date": "2024-11-13T21:56:45.868Z"
    },
    {
      "id": "8d36",
      "userId": "f7c8",
      "date": "2024-11-13T21:57:09.761Z"
    },
    {
      "id": "5ced",
      "userId": "f7c8",
      "date": "2024-11-13T22:14:00.786Z"
    },
    {
      "id": "d24c",
      "userId": "f7c8",
      "date": "2024-11-13T22:26:14.534Z"
    }
  ]
}